{
  "status": "Cancelled",
  "version": 3,
  "id": "b803d4b6-6d7f-4604-99e6-065f33624344",
  "created_at": "2023-07-23T13:40:57Z",
  "updated_at": "2024-02-19T16:29:17Z",
  "client_created_at": "2023-07-23T13:40:57Z",
  "client_updated_at": "2024-02-19T16:29:15Z",
  "created_by": "Jon Barton",
  "created_by_id": "c74ae54d-e0e3-475f-956f-6b6a23e88ce2",
  "updated_by": "Jon Barton",
  "updated_by_id": "c74ae54d-e0e3-475f-956f-6b6a23e88ce2",
  "created_location": null,
  "updated_location": null,
  "created_duration": null,
  "updated_duration": 2,
  "edited_duration": 2,
  "form_id": "8b47f113-c60f-4016-af20-1a4367887eba",
  "project_id": null,
  "record_series_id": null,
  "assigned_to": null,
  "assigned_to_id": null,
  "form_values": {
    "96e4": [
      {
        "record_id": "34254510-cd78-4814-9870-1c46559cfc38"
      }
    ],
    "c4ee": "Q454 OLD RECORD DO NOT USE",
    "48ca": {
      "sub_thoroughfare": "7",
      "thoroughfare": "Bulwar Road ",
      "suite": null,
      "locality": null,
      "sub_admin_area": null,
      "admin_area": null,
      "postal_code": "EN5 5BU",
      "country": null
    },
    "4a82": "Private Residential,House,Terrace",
    "7d46": "No other properties included",
    "9c58": "No service visits have taken place",
    "5b45": [
      {
        "caption": null,
        "photo_id": "67011743-3042-4d2d-947e-9c212635a01d"
      }
    ]
  },
  "latitude": 51.6518729144,
  "longitude": -0.177389185754,
  "altitude": null,
  "geometry": {
    "type": "Point",
    "coordinates": [
      -0.17738918575385365,
      51.65187291435625
    ]
  },
  "speed": null,
  "course": null,
  "horizontal_accuracy": null,
  "vertical_accuracy": null,
  "system_status": null
}