{
  "status": "Ongoing",
  "version": 6,
  "id": "0fe06c67-1dd9-4980-9533-eb476236c66b",
  "created_at": "2023-07-23T13:05:23Z",
  "updated_at": "2023-10-24T07:24:29Z",
  "client_created_at": "2023-07-23T13:05:23Z",
  "client_updated_at": "2023-10-24T07:24:24Z",
  "created_by": "Jon Barton",
  "created_by_id": "c74ae54d-e0e3-475f-956f-6b6a23e88ce2",
  "updated_by": "Jon Barton",
  "updated_by_id": "c74ae54d-e0e3-475f-956f-6b6a23e88ce2",
  "created_location": null,
  "updated_location": {
    "latitude": 51.4522226942997,
    "longitude": -0.06562123596202281,
    "altitude": 39.07999492343515,
    "horizontal_accuracy": 4.750266778969676
  },
  "created_duration": null,
  "updated_duration": 47909,
  "edited_duration": 48077,
  "form_id": "8b47f113-c60f-4016-af20-1a4367887eba",
  "project_id": null,
  "record_series_id": null,
  "assigned_to": null,
  "assigned_to_id": null,
  "form_values": {
    "96e4": [
      {
        "record_id": "f4b36b4c-4eee-49fa-8c42-ff8b3cd768d3"
      }
    ],
    "c4ee": "Q8314",
    "48ca": {
      "sub_thoroughfare": "251",
      "thoroughfare": "Underhill Road",
      "suite": null,
      "locality": "London",
      "sub_admin_area": null,
      "admin_area": null,
      "postal_code": "SE22 OPB",
      "country": null
    },
    "4a82": "Private Residential,House,Semi",
    "19ac": "Stand 1 - Knotweed in rear garden by shed buildings right corner.\nStand 2 - In neighbouring property No 253 along fence line and one/two stems growing through patio hardstanding. Nothing visible in No 249 however view mostly obstructed view green vegetation. Leaflets posted in both homes.",
    "3bdb": [
      {
        "latitude": 51.4521697,
        "longitude": -0.0660802,
        "form_values": {
          "4010": {
            "other_values": [],
            "choice_values": [
              "Japanese Knotweed Management Record"
            ]
          },
          "b0b0": {
            "other_values": [],
            "choice_values": [
              "Herbicide Application & Monitoring Record"
            ]
          },
          "8eaf": "2018-08-22",
          "2a76": "09:50",
          "385f": {
            "other_values": [],
            "choice_values": [
              "Jan Aslanowicz"
            ]
          },
          "84ea": {
            "other_values": [],
            "choice_values": [
              "No wind",
              "Intermittent cloud",
              "Between 15 and 20 degrees centigrade"
            ]
          },
          "c4b3": "yes",
          "6da0": "yes",
          "3fd4": {
            "other_values": [],
            "choice_values": [
              "Japanese knotweed"
            ]
          },
          "2073": "Invasive weed control (Japanese knotweed)",
          "3bb5": "Not applicable",
          "8f2a": {
            "other_values": [],
            "choice_values": [
              "Face protection",
              "Protective suit",
              "Protective gloves",
              "Boots"
            ]
          },
          "b65a": {
            "other_values": [],
            "choice_values": [
              "RoundUp Pro-Vantage 480",
              " 15534",
              " Glyphosate"
            ]
          },
          "22b1": "37.5",
          "5b61": "3",
          "7644": {
            "other_values": [],
            "choice_values": [
              "yes"
            ]
          },
          "2d29": "Knotweed treated in rear garden today"
        },
        "id": "3e02b445-862c-4c72-82cf-dc44c849af54",
        "created_at": "1680957078",
        "updated_at": "1680957078",
        "geometry": {
          "type": "Point",
          "coordinates": [
            -0.0660802,
            51.4521697
          ]
        },
        "created_duration": null,
        "updated_duration": null,
        "edited_duration": null,
        "version": 3,
        "created_by_id": "c74ae54d-e0e3-475f-956f-6b6a23e88ce2",
        "updated_by_id": "c74ae54d-e0e3-475f-956f-6b6a23e88ce2",
        "changeset_id": "24e52366-8db8-442b-83ea-530e10e100f7",
        "draft": false
      },
      {
        "latitude": 51.452179,
        "longitude": -0.06614580000000002,
        "form_values": {
          "4010": {
            "other_values": [],
            "choice_values": [
              "Japanese Knotweed Management Record"
            ]
          },
          "b0b0": {
            "other_values": [],
            "choice_values": [
              "Herbicide Application & Monitoring Record"
            ]
          },
          "8eaf": "2019-06-03",
          "2a76": "10:55",
          "385f": {
            "other_values": [],
            "choice_values": [
              "Jan Aslanowicz"
            ]
          },
          "84ea": {
            "other_values": [],
            "choice_values": [
              "Light breeze",
              "Hazy sun",
              "Between 5 and 15 degrees centigrade"
            ]
          },
          "2c03": {
            "other_values": [],
            "choice_values": [
              "No visible knotweed growth to treat"
            ]
          },
          "c4b3": "yes",
          "6da0": "no",
          "3bb5": "Not applicable",
          "e77c": [
            {
              "photo_id": "9dcb33e0-bf88-4685-b0d5-de0599eee34a",
              "caption": null
            },
            {
              "photo_id": "f6230760-3b41-4168-9dcc-cfb6e3bc1eae",
              "caption": null
            }
          ]
        },
        "id": "6cc4f56f-6233-4f56-8096-6037213215ff",
        "created_at": "1680957078",
        "updated_at": "1680957078",
        "geometry": {
          "type": "Point",
          "coordinates": [
            -0.06614580000000002,
            51.452179
          ]
        },
        "created_duration": null,
        "updated_duration": null,
        "edited_duration": null,
        "version": 3,
        "created_by_id": "c74ae54d-e0e3-475f-956f-6b6a23e88ce2",
        "updated_by_id": "c74ae54d-e0e3-475f-956f-6b6a23e88ce2",
        "changeset_id": "24e52366-8db8-442b-83ea-530e10e100f7",
        "draft": false
      },
      {
        "latitude": 51.4522237,
        "longitude": -0.0660105,
        "form_values": {
          "4010": {
            "other_values": [],
            "choice_values": [
              "Japanese Knotweed Management Record"
            ]
          },
          "b0b0": {
            "other_values": [],
            "choice_values": [
              "Herbicide Application & Monitoring Record"
            ]
          },
          "45b7": {
            "other_values": [],
            "choice_values": [
              "Scheduled Treatment"
            ]
          },
          "8eaf": "2019-09-05",
          "2a76": "12:01",
          "385f": {
            "other_values": [],
            "choice_values": [
              "Jan Aslanowicz"
            ]
          },
          "84ea": {
            "other_values": [],
            "choice_values": [
              "No wind",
              "Sunny",
              "Between 15 and 20 degrees centigrade"
            ]
          },
          "2c03": {
            "other_values": [],
            "choice_values": [
              "No visible knotweed growth to treat"
            ]
          },
          "c4b3": "yes",
          "6da0": "no",
          "3bb5": "Not applicable",
          "e77c": [
            {
              "photo_id": "44da75b5-ae97-49a8-837f-69d6bd2d3316",
              "caption": null
            },
            {
              "photo_id": "b2cbe010-f709-4ad0-853a-a138023f79c6",
              "caption": null
            }
          ]
        },
        "id": "c5a28de7-302e-4fc3-beae-6e388f9c0bd2",
        "created_at": "1680957078",
        "updated_at": "1680957078",
        "geometry": {
          "type": "Point",
          "coordinates": [
            -0.0660105,
            51.4522237
          ]
        },
        "created_duration": null,
        "updated_duration": null,
        "edited_duration": null,
        "version": 3,
        "created_by_id": "c74ae54d-e0e3-475f-956f-6b6a23e88ce2",
        "updated_by_id": "c74ae54d-e0e3-475f-956f-6b6a23e88ce2",
        "changeset_id": "24e52366-8db8-442b-83ea-530e10e100f7",
        "draft": false
      },
      {
        "latitude": 51.4523583199934,
        "longitude": -0.06574074069933314,
        "form_values": {
          "4010": {
            "other_values": [],
            "choice_values": [
              "Japanese Knotweed Management Record"
            ]
          },
          "b0b0": {
            "other_values": [],
            "choice_values": [
              "Herbicide Application & Monitoring Record"
            ]
          },
          "45b7": {
            "other_values": [],
            "choice_values": [
              "Scheduled Treatment"
            ]
          },
          "8eaf": "2020-06-04",
          "2a76": "14:06",
          "385f": {
            "other_values": [],
            "choice_values": [
              "Phil Walker. CSJK. PCAQT.  NPTC 410111, PA1 PA6AW"
            ]
          },
          "2c03": {
            "other_values": [],
            "choice_values": [
              "No visible knotweed growth to treat"
            ]
          },
          "c4b3": "yes",
          "6da0": "no",
          "3bb5": "Not applicable",
          "2d29": "No active JK within target property or neighbouring garden. There is however knotweed present within 175 Upland Road - have told their neighbour that I was chatting too that we would post them a letter out.",
          "e77c": [
            {
              "photo_id": "377cb313-c2ce-4cd0-ab02-2438383fa2ac",
              "caption": null
            },
            {
              "photo_id": "52011574-cd90-4450-b689-efb8c9578b06",
              "caption": null
            },
            {
              "photo_id": "f311081a-d990-4f93-a210-be18fee60475",
              "caption": null
            },
            {
              "photo_id": "5a03fb22-4a2b-45e6-9285-4a97a3db451c",
              "caption": null
            },
            {
              "photo_id": "618a0acd-e8e3-43db-b217-19b52e65c594",
              "caption": null
            },
            {
              "photo_id": "a64a85fd-38fd-4d31-9bf5-2ba0992841f3",
              "caption": null
            },
            {
              "photo_id": "375d1186-0a36-400c-92da-e97d9a2718f5",
              "caption": "175 upland road"
            },
            {
              "photo_id": "584c8eab-72ea-46c1-9ed0-502ac236103b",
              "caption": null
            },
            {
              "photo_id": "1e0fd7e3-1173-4d30-8d80-1fb64fd62c25",
              "caption": null
            },
            {
              "photo_id": "497f88d6-08fb-4dac-8c0c-4a5462dd7a68",
              "caption": null
            },
            {
              "photo_id": "595aabd2-6d08-4606-ab5a-c6050edec7ef",
              "caption": null
            },
            {
              "photo_id": "41a791da-cbc5-4195-99e3-d60ce963e9e0",
              "caption": null
            }
          ]
        },
        "id": "aeab2abd-768a-48c7-81cb-4dd624050afb",
        "created_at": "1680957078",
        "updated_at": "1680957078",
        "geometry": {
          "type": "Point",
          "coordinates": [
            -0.06574074069933314,
            51.4523583199934
          ]
        },
        "created_duration": null,
        "updated_duration": null,
        "edited_duration": null,
        "version": 4,
        "created_by_id": "c74ae54d-e0e3-475f-956f-6b6a23e88ce2",
        "updated_by_id": "c74ae54d-e0e3-475f-956f-6b6a23e88ce2",
        "changeset_id": "24e52366-8db8-442b-83ea-530e10e100f7",
        "draft": false
      },
      {
        "latitude": 51.45222118583523,
        "longitude": -0.06600882467905436,
        "form_values": {
          "4010": {
            "other_values": [],
            "choice_values": [
              "Japanese Knotweed Management Record"
            ]
          },
          "b0b0": {
            "other_values": [],
            "choice_values": [
              "Herbicide Application & Monitoring Record"
            ]
          },
          "45b7": {
            "other_values": [],
            "choice_values": [
              "Scheduled Treatment"
            ]
          },
          "8eaf": "2020-09-17",
          "2a76": "11:08",
          "385f": {
            "other_values": [],
            "choice_values": [
              "Jon Barton. CSJK. PCAQT. NPTC 499877, PA1 PA6AW"
            ]
          },
          "84ea": {
            "other_values": [],
            "choice_values": [
              "Sunny",
              "Light breeze"
            ]
          },
          "2c03": {
            "other_values": [],
            "choice_values": [
              "No visible knotweed growth to treat"
            ]
          },
          "c4b3": "yes",
          "6da0": "no",
          "3bb5": "Not applicable",
          "2d29": "Inspected garden for Knotweed and nothing found",
          "e77c": [
            {
              "photo_id": "7fb3893f-8e42-4287-8014-1039449f154c",
              "caption": "Location of original growths of knotweed "
            }
          ]
        },
        "id": "83d3894d-83e8-4dc4-8c1b-20773a92e068",
        "created_at": "1680957078",
        "updated_at": "1680957078",
        "geometry": {
          "type": "Point",
          "coordinates": [
            -0.06600882467905436,
            51.45222118583523
          ]
        },
        "created_duration": null,
        "updated_duration": null,
        "edited_duration": null,
        "version": 4,
        "created_by_id": "c74ae54d-e0e3-475f-956f-6b6a23e88ce2",
        "updated_by_id": "c74ae54d-e0e3-475f-956f-6b6a23e88ce2",
        "changeset_id": "24e52366-8db8-442b-83ea-530e10e100f7",
        "draft": false
      },
      {
        "latitude": 51.45211632808596,
        "longitude": -0.06616598987735356,
        "form_values": {
          "4010": {
            "other_values": [],
            "choice_values": [
              "Japanese Knotweed Management Record"
            ]
          },
          "b0b0": {
            "other_values": [],
            "choice_values": [
              "Herbicide Application & Monitoring Record"
            ]
          },
          "8eaf": "2021-06-21",
          "385f": {
            "other_values": [],
            "choice_values": [
              "Matthew Patrycy. PCAQT. NPTC 353281 (PA1 PA6A)"
            ]
          },
          "84ea": {
            "other_values": [],
            "choice_values": [
              "Rain (showers)",
              "Rain (persistent)"
            ]
          },
          "2c03": {
            "other_values": [
              "Too wet for treatment "
            ],
            "choice_values": [
              "See weather conditions entry"
            ]
          },
          "c4b3": "yes",
          "6da0": "no",
          "3bb5": "Not applicable",
          "2d29": "Mature healthy jk stem was observed behind the shed coming from neighbouring garden.",
          "e77c": [
            {
              "photo_id": "fe5b181e-a41c-46ee-b34c-a3200e21e689",
              "caption": null
            },
            {
              "photo_id": "72924010-a2ee-45ac-8c7c-8007e552747c",
              "caption": null
            },
            {
              "photo_id": "2fab584f-4383-4af0-8fd8-cc480982127c",
              "caption": null
            },
            {
              "photo_id": "98a1cc6f-c1b9-493e-af5d-74586bf970bd",
              "caption": null
            }
          ]
        },
        "id": "34c42ba7-14cb-4265-a358-02158c5c4db6",
        "created_at": "1680957078",
        "updated_at": "1680957078",
        "geometry": {
          "type": "Point",
          "coordinates": [
            -0.06616598987735356,
            51.45211632808596
          ]
        },
        "created_duration": null,
        "updated_duration": null,
        "edited_duration": null,
        "version": 4,
        "created_by_id": "c74ae54d-e0e3-475f-956f-6b6a23e88ce2",
        "updated_by_id": "c74ae54d-e0e3-475f-956f-6b6a23e88ce2",
        "changeset_id": "24e52366-8db8-442b-83ea-530e10e100f7",
        "draft": false
      },
      {
        "latitude": 51.452438098846976,
        "longitude": -0.06575368003637766,
        "form_values": {
          "4010": {
            "other_values": [],
            "choice_values": [
              "Japanese Knotweed Management Record"
            ]
          },
          "b0b0": {
            "other_values": [],
            "choice_values": [
              "Herbicide Application & Monitoring Record"
            ]
          },
          "45b7": {
            "other_values": [],
            "choice_values": [
              "Scheduled Treatment"
            ]
          },
          "8eaf": "2021-10-08",
          "2a76": "10:50",
          "385f": {
            "other_values": [],
            "choice_values": [
              "Phil Walker. CSJK. PCAQT.  NPTC 410111, PA1 PA6AW"
            ]
          },
          "84ea": {
            "other_values": [],
            "choice_values": [
              "No wind",
              "Overcast",
              "Between 15 and 20 degrees centigrade"
            ]
          },
          "c4b3": "yes",
          "6da0": "yes",
          "3fd4": {
            "other_values": [],
            "choice_values": [
              "Japanese knotweed"
            ]
          },
          "2073": "Invasive weed control (Japanese knotweed)",
          "3bb5": "Not applicable",
          "48f0": {
            "other_values": [],
            "choice_values": [
              "Very stunted stems",
              "Green leaves"
            ]
          },
          "8f2a": {
            "other_values": [],
            "choice_values": [
              "Boots",
              "Protective gloves"
            ]
          },
          "b65a": {
            "other_values": [],
            "choice_values": [
              "RoundUp Pro-Vantage 480",
              " 15534",
              " Glyphosate"
            ]
          },
          "22b1": "37.5",
          "5b61": "0.2",
          "7644": {
            "other_values": [],
            "choice_values": [
              "yes"
            ]
          },
          "2d29": "Shed has been removed and disturbance caused to the treatment area.\n\nJK plants that were present last visit have been cut back.\n\nOn small area bonsai treat as well as spray over of treatment area.",
          "e77c": [
            {
              "photo_id": "331c55d2-702d-4d11-95e8-7de879506440",
              "caption": null
            },
            {
              "photo_id": "944ec513-0609-4ff2-92dc-2f8725c46a7e",
              "caption": null
            },
            {
              "photo_id": "a22eaaa0-b5a0-46b8-b89c-256adb87364a",
              "caption": null
            },
            {
              "photo_id": "a12b2022-0e1d-400e-af6d-4b3fac0d82b8",
              "caption": null
            },
            {
              "photo_id": "749b31e6-cf16-4182-a910-847730a522a0",
              "caption": null
            },
            {
              "photo_id": "25d6378d-12c6-48a4-a601-f5ed490f823f",
              "caption": null
            },
            {
              "photo_id": "ad186e81-30ec-49c0-be96-2059e25577d4",
              "caption": null
            },
            {
              "photo_id": "fa71529b-1dad-4043-8c55-5685d343938d",
              "caption": null
            },
            {
              "photo_id": "e7cf6aaf-96ea-4fa4-be5b-6a21f2bd6494",
              "caption": null
            },
            {
              "photo_id": "8bbb6c80-89ce-49a1-8e3c-f085086d5d59",
              "caption": null
            },
            {
              "photo_id": "6c79a1b5-832f-43b9-99be-93da8aa364b4",
              "caption": null
            },
            {
              "photo_id": "0133f977-fb6b-4df8-9db1-3fcee328d5ac",
              "caption": null
            },
            {
              "photo_id": "5a648120-63ce-416d-934f-5ac53a3c1c30",
              "caption": null
            },
            {
              "photo_id": "3875838b-fa72-4ae1-850e-832301078761",
              "caption": null
            },
            {
              "photo_id": "3b7df82b-be80-42cc-a4ff-8c5ac0d72d43",
              "caption": null
            },
            {
              "photo_id": "8a5cd388-ef34-460a-b2af-9eb778edde77",
              "caption": null
            },
            {
              "photo_id": "c918131c-d544-4702-a9c0-cf07c59c0d53",
              "caption": null
            },
            {
              "photo_id": "98315417-b74e-4f27-b080-feca0f560bac",
              "caption": null
            }
          ]
        },
        "id": "e2ba9bbe-4a38-4944-aa32-95d294c87dc5",
        "created_at": "1680957078",
        "updated_at": "1680957078",
        "geometry": {
          "type": "Point",
          "coordinates": [
            -0.06575368003637766,
            51.452438098846976
          ]
        },
        "created_duration": null,
        "updated_duration": 39,
        "edited_duration": 39,
        "version": 4,
        "created_by_id": "c74ae54d-e0e3-475f-956f-6b6a23e88ce2",
        "updated_by_id": "c74ae54d-e0e3-475f-956f-6b6a23e88ce2",
        "changeset_id": "24e52366-8db8-442b-83ea-530e10e100f7",
        "draft": false,
        "updated_location": {
          "latitude": 52.040776913724144,
          "longitude": 0.4861287591383789,
          "altitude": 96.22744565457106,
          "horizontal_accuracy": 4.7385069012298136
        }
      },
      {
        "latitude": 51.45232466855752,
        "longitude": -0.06570629938234751,
        "form_values": {
          "4010": {
            "other_values": [],
            "choice_values": [
              "Japanese Knotweed Management Record"
            ]
          },
          "b0b0": {
            "other_values": [],
            "choice_values": [
              "Herbicide Application & Monitoring Record"
            ]
          },
          "45b7": {
            "other_values": [],
            "choice_values": [
              "Scheduled Treatment"
            ]
          },
          "8eaf": "2022-07-20",
          "2a76": "09:13",
          "385f": {
            "other_values": [],
            "choice_values": [
              "Phil Walker. CSJK. PCAQT.  NPTC 410111, PA1 PA6AW"
            ]
          },
          "84ea": {
            "other_values": [],
            "choice_values": [
              "No wind",
              "Sunny",
              "Between 20 and 25 degrees centigrade"
            ]
          },
          "c4b3": "yes",
          "6da0": "yes",
          "3fd4": {
            "other_values": [],
            "choice_values": [
              "Japanese knotweed"
            ]
          },
          "2073": "Invasive weed control (Japanese knotweed)",
          "3bb5": "Not applicable",
          "48f0": {
            "other_values": [],
            "choice_values": [
              "Full height stems (min 1.5 metres)",
              "Stunted stems",
              "Fully developed leaves",
              "Green leaves"
            ]
          },
          "8f2a": {
            "other_values": [],
            "choice_values": [
              "Boots",
              "Protective gloves"
            ]
          },
          "b65a": {
            "other_values": [],
            "choice_values": [
              "RoundUp Pro-Vantage 480",
              " 15534",
              " Glyphosate"
            ]
          },
          "22b1": "37.5",
          "5b61": "0.5",
          "7644": {
            "other_values": [],
            "choice_values": [
              "yes"
            ]
          },
          "2d29": "Sprayed off active JK growth and treatment area ",
          "e77c": [
            {
              "photo_id": "21de2f8f-39d0-4077-9cff-7de92d574e96",
              "caption": null
            },
            {
              "photo_id": "8aa84d3f-da9a-4864-bed5-3473a7caac0f",
              "caption": null
            },
            {
              "photo_id": "8bc7a677-571d-4e0c-83a4-75702553f6f5",
              "caption": null
            },
            {
              "photo_id": "c004218b-f321-486d-83ce-aaa50b0c00f5",
              "caption": null
            },
            {
              "photo_id": "257d7fb8-3c86-4010-9b5a-9b2c6ec8f547",
              "caption": null
            },
            {
              "photo_id": "62a33102-f828-401f-b178-dbd0aac73cb2",
              "caption": null
            },
            {
              "photo_id": "9b7ba1b8-160c-4be2-8036-a4e74f3ede4b",
              "caption": null
            },
            {
              "photo_id": "d9436cca-cc69-402f-8b2e-749b6c64cb5f",
              "caption": null
            },
            {
              "photo_id": "3167b116-da7f-4f11-8f86-f650f0b25c66",
              "caption": null
            }
          ]
        },
        "id": "7e336f85-1b54-4345-99ad-4fe80932abe3",
        "created_at": "1680957078",
        "updated_at": "1680957078",
        "geometry": {
          "type": "Point",
          "coordinates": [
            -0.06570629938234751,
            51.45232466855752
          ]
        },
        "created_duration": null,
        "updated_duration": null,
        "edited_duration": null,
        "version": 4,
        "created_by_id": "c74ae54d-e0e3-475f-956f-6b6a23e88ce2",
        "updated_by_id": "c74ae54d-e0e3-475f-956f-6b6a23e88ce2",
        "changeset_id": "24e52366-8db8-442b-83ea-530e10e100f7",
        "draft": false
      },
      {
        "created_location": {
          "latitude": 51.45231821204268,
          "longitude": -0.06554749255968889,
          "altitude": 35.59215545654297,
          "horizontal_accuracy": 35
        },
        "id": "ef9b61fd-ea80-49dc-a853-fc0d51fef1fa",
        "created_at": "1698131921",
        "draft": false,
        "form_values": {
          "1128": "yes",
          "8eaf": "2023-10-24",
          "b0b0": {
            "other_values": [],
            "choice_values": [
              "Herbicide Application & Monitoring Record"
            ]
          },
          "2d29": "No active JK growth seen withinn target property garden, there is some growing immediately adjacent to the rear boundary fence in the garden over to the rear right hand side",
          "4010": {
            "other_values": [],
            "choice_values": [
              "Japanese Knotweed Management Record"
            ]
          },
          "ebc0": {
            "other_values": [],
            "choice_values": [
              "No visible knotweed growth to treat"
            ]
          },
          "385f": {
            "other_values": [],
            "choice_values": [
              "Phil Walker"
            ]
          },
          "e77c": [
            {
              "caption": "251",
              "photo_id": "e003ac28-7852-46e9-bcb5-e46592b1414c"
            },
            {
              "caption": "251",
              "photo_id": "2e4ca5de-9e95-4c76-8144-10beff5df209"
            },
            {
              "caption": "251",
              "photo_id": "1ec2d62b-29b4-4e20-9f39-cd6c5b21dc07"
            },
            {
              "caption": "251",
              "photo_id": "d67201dd-e0e2-46a1-a0a3-a9a0d1d07eef"
            },
            {
              "caption": "251",
              "photo_id": "7591cfd0-2b0f-4894-a105-4e831e91d251"
            },
            {
              "caption": "251",
              "photo_id": "d41c4657-7d8b-400c-b284-49c25f45b915"
            },
            {
              "caption": "Behind neighbouring right hand side property outbuilding ",
              "photo_id": "92046696-7d73-417d-998c-545b3273c5df"
            },
            {
              "caption": "Active JK growth over rear boundary fence",
              "photo_id": "6ef3208b-a452-4d39-945e-693df74487a7"
            },
            {
              "caption": "251",
              "photo_id": "d3117e0a-6c43-47b0-a208-68d2172dd14c"
            },
            {
              "caption": "JK present over rear boundary fence (right hand garden as stood with back to target).",
              "photo_id": "e084d761-bd61-4caf-b358-7ea1d46d1d55"
            },
            {
              "caption": "251",
              "photo_id": "69b21c66-b629-4937-9bd1-6bdc704a8f27"
            }
          ],
          "2a76": "08:00",
          "8885": {
            "other_values": [],
            "choice_values": [
              "Site only"
            ]
          },
          "45b7": {
            "other_values": [],
            "choice_values": [
              "Herbicide treatment (spray)"
            ]
          },
          "84ea": {
            "other_values": [],
            "choice_values": [
              "No wind",
              "Heavy cloud",
              "Drizzle"
            ]
          },
          "6da0": "no",
          "ac6f": "9",
          "c4b3": "yes"
        },
        "geometry": {
          "type": "Point",
          "coordinates": [
            -0.06554749255968889,
            51.45231821204268
          ]
        },
        "updated_location": {
          "latitude": 51.45221350894653,
          "longitude": -0.06561529851356689,
          "altitude": 39.270342379808426,
          "horizontal_accuracy": 4.750053545804068
        },
        "updated_at": "1698132262",
        "created_duration": 341,
        "updated_duration": 341,
        "edited_duration": 341,
        "version": 1,
        "created_by_id": "c74ae54d-e0e3-475f-956f-6b6a23e88ce2",
        "updated_by_id": "c74ae54d-e0e3-475f-956f-6b6a23e88ce2",
        "changeset_id": "24e52366-8db8-442b-83ea-530e10e100f7"
      }
    ],
    "7d46": "No other properties included",
    "5b45": [
      {
        "caption": null,
        "photo_id": "bad0a639-9d06-41ff-89c7-51f7b1806c86"
      },
      {
        "photo_id": "cfa12f1f-1aec-497c-95ad-a098318a4895",
        "caption": null
      }
    ],
    "da65": "24/10/2023",
    "793c": "No monitoring visits have taken place",
    "9c58": "undefined:  22/08/2018, undefined\nundefined:  03/06/2019, undefined\nundefined:  05/09/2019, Scheduled Treatment\nundefined:  04/06/2020, Scheduled Treatment\nundefined:  17/09/2020, Scheduled Treatment\nundefined:  21/06/2021, undefined\nundefined:  08/10/2021, Scheduled Treatment\nundefined:  20/07/2022, Scheduled Treatment\n9:  24/10/2023, Herbicide treatment (spray)",
    "2e97": "9"
  },
  "latitude": 51.452478,
  "longitude": -0.0657843,
  "altitude": null,
  "geometry": {
    "type": "Point",
    "coordinates": [
      -0.0657843,
      51.452478
    ]
  },
  "speed": null,
  "course": null,
  "horizontal_accuracy": null,
  "vertical_accuracy": null,
  "system_status": null
}