{
  "status": "Pending",
  "version": 3,
  "id": "765567b0-dccf-4c9b-bf69-2f4e097b4458",
  "created_at": "2023-07-23T13:29:00Z",
  "updated_at": "2023-08-05T11:52:02Z",
  "client_created_at": "2023-07-23T13:29:00Z",
  "client_updated_at": "2023-07-23T13:29:00Z",
  "created_by": "Jon Barton",
  "created_by_id": "c74ae54d-e0e3-475f-956f-6b6a23e88ce2",
  "updated_by": "Jon Barton",
  "updated_by_id": "c74ae54d-e0e3-475f-956f-6b6a23e88ce2",
  "created_location": null,
  "updated_location": null,
  "created_duration": null,
  "updated_duration": null,
  "edited_duration": null,
  "form_id": "8b47f113-c60f-4016-af20-1a4367887eba",
  "project_id": null,
  "record_series_id": null,
  "assigned_to": null,
  "assigned_to_id": null,
  "form_values": {
    "96e4": [
      {
        "record_id": "ad650874-2664-44d9-9126-c88ad2bd8dba"
      }
    ],
    "c4ee": "Q- Brent housing ",
    "48ca": {
      "sub_thoroughfare": "8A",
      "thoroughfare": "Deacon Road",
      "suite": "",
      "locality": "London",
      "sub_admin_area": "Greater London",
      "admin_area": "England",
      "postal_code": "NW2 5QH",
      "country": "United Kingdom"
    },
    "4a82": "Housing Association,Flat / Apartment / Maisonette",
    "3bdb": [
      {
        "latitude": 51.5505199,
        "longitude": -0.2349432,
        "form_values": {
          "4010": {
            "other_values": [],
            "choice_values": [
              "Japanese Knotweed Management Record"
            ]
          },
          "b0b0": {
            "other_values": [],
            "choice_values": [
              "Herbicide Application & Monitoring Record"
            ]
          },
          "1db0": {
            "other_values": [],
            "choice_values": []
          },
          "45b7": {
            "other_values": [],
            "choice_values": []
          },
          "113b": {
            "other_values": [],
            "choice_values": []
          },
          "9530": {
            "other_values": [],
            "choice_values": []
          },
          "5c53": {
            "other_values": [],
            "choice_values": []
          },
          "e29a": {
            "other_values": [],
            "choice_values": []
          },
          "8eaf": "2017-08-01",
          "2a76": "10:30",
          "385f": {
            "other_values": [],
            "choice_values": [
              "Jan Aslanowicz"
            ]
          },
          "8885": {
            "other_values": [],
            "choice_values": []
          },
          "84ea": {
            "other_values": [],
            "choice_values": [
              "Light breeze",
              "Sunny",
              "Between 15 and 20 degrees centigrade"
            ]
          },
          "2c03": {
            "other_values": [],
            "choice_values": [
              "No visible knotweed growth to treat"
            ]
          },
          "c4b3": "yes",
          "6da0": "no",
          "ebc0": {
            "other_values": [],
            "choice_values": []
          },
          "3fd4": {
            "other_values": [],
            "choice_values": []
          },
          "3bb5": "Not applicable",
          "48f0": {
            "other_values": [],
            "choice_values": []
          },
          "eaeb": {
            "other_values": [],
            "choice_values": []
          },
          "8f2a": {
            "other_values": [],
            "choice_values": []
          },
          "b65a": {
            "other_values": [],
            "choice_values": []
          },
          "7644": {
            "other_values": [],
            "choice_values": []
          },
          "2d29": "Also no visable knotweed in adjoining property 8",
          "e77c": [
            {
              "photo_id": "50b8d922-c34d-427b-82d8-96959e07b294",
              "caption": ""
            },
            {
              "photo_id": "84c061dd-5179-4748-9a68-edd9154a2305",
              "caption": ""
            },
            {
              "photo_id": "c967be59-5a79-48f3-9004-425020b28028",
              "caption": ""
            },
            {
              "photo_id": "872ea0f6-cc52-410b-930f-bbe8535bd120",
              "caption": ""
            },
            {
              "photo_id": "0b84736b-c5db-44d9-bfb1-f5d6dd8dc3fc",
              "caption": ""
            },
            {
              "photo_id": "8e759c36-0c0e-407c-9af8-3836f9c76844",
              "caption": ""
            }
          ],
          "5440": {
            "other_values": [],
            "choice_values": []
          },
          "1de3": {
            "other_values": [],
            "choice_values": []
          },
          "15a4": {
            "other_values": [],
            "choice_values": []
          }
        },
        "id": "c38b0f25-4de4-4068-8564-62e008e69185",
        "created_at": "1680956863",
        "updated_at": "1680956863",
        "geometry": null,
        "created_duration": null,
        "updated_duration": null,
        "edited_duration": null,
        "version": 1,
        "created_by_id": "c74ae54d-e0e3-475f-956f-6b6a23e88ce2",
        "updated_by_id": "c74ae54d-e0e3-475f-956f-6b6a23e88ce2",
        "changeset_id": null
      }
    ],
    "5b45": [
      {
        "photo_id": "8f4b1352-1c0e-484f-abb3-6d469f08fadb",
        "caption": null
      }
    ]
  },
  "latitude": 51.5504788,
  "longitude": -0.2352084,
  "altitude": null,
  "geometry": {
    "type": "Point",
    "coordinates": [
      -0.2352084,
      51.5504788
    ]
  },
  "speed": null,
  "course": null,
  "horizontal_accuracy": null,
  "vertical_accuracy": null,
  "system_status": null
}